dparcel/__init__.py
dparcel/environment.py
dparcel/parcel.py
dparcel/thermo.py
dparcel-0.1.dist-info/LICENSE
dparcel-0.1.dist-info/METADATA
dparcel-0.1.dist-info/WHEEL
dparcel-0.1.dist-info/top_level.txt
dparcel-0.1.dist-info/RECORD
