Metadata-Version: 2.1
Name: dparcel
Version: 0.1
Summary: A simple parcel theory model of downdrafts in atmospheric convection.
Home-page: https://github.com/climate-enigma/dparcel
Author: Thomas Schanzer
Author-email: t.schanzer@student.unsw.edu.au
License: BSD 3-Clause License
Project-URL: Documentation, https://dparcel.readthedocs.io/
Project-URL: Source Code, https://github.com/climate-enigma/dparcel
Project-URL: Bug Tracker, https://github.com/climate-enigma/dparcel/issues
Project-URL: Release Notes, https://github.com/climate-enigma/dparcel/releases
Keywords: parcel downdraft atmosphere convection model
Platform: UNKNOWN
Classifier: License :: OSI Approved :: BSD License
Classifier: Development Status :: 4 - Beta
Classifier: Intended Audience :: Science/Research
Classifier: Natural Language :: English
Classifier: Programming Language :: Python :: 3.8
Classifier: Topic :: Scientific/Engineering :: Atmospheric Science
License-File: LICENSE
Requires-Dist: numpy
Requires-Dist: metpy (>=1.2)
Requires-Dist: scipy
